.gitignore
README.md
requirements.txt
setup.py
templates/README.md
tinyj2/__init__.py
tinyj2/__main__.py
tinyj2.egg-info/PKG-INFO
tinyj2.egg-info/SOURCES.txt
tinyj2.egg-info/dependency_links.txt
tinyj2.egg-info/entry_points.txt
tinyj2.egg-info/requires.txt
tinyj2.egg-info/top_level.txt