Metadata-Version: 1.0
Name: tinyj2
Version: 0.3.0
Summary: tinyj2 - tiny renderer for jinja templates
Home-page: UNKNOWN
Author: Wojciech Wróblewski
Author-email: wojciech.wroblewski@gmx.com
License: UNKNOWN
Platform: UNKNOWN
